dli_scrapping_lib/__init__.py
dli_scrapping_lib/scrap/__init__.py
dli_scrapping_lib/scrap/scrap.py
dli_scrapping_lib/setup.py
dli_scrapping_lib/util/__init__.py
dli_scrapping_lib/util/util.py
dli_scrapping_lib-1.0.4.dist-info/WHEEL
dli_scrapping_lib-1.0.4.dist-info/METADATA
dli_scrapping_lib-1.0.4.dist-info/RECORD
